sg_core/__init__.py
sg_core/adapters.py
sg_core/decision_loop.py
sg_core/models.py
sg_core/obligation_adapter.py
sg_core/obligations.py
sg_core/pause_api.py
sg_core/policy.py
sg_core/py.typed
sg_core/adapters/__init__.py
sg_core/adapters/approvals.py
sg_core/audit/__init__.py
sg_core/audit/sink.py
sg_core/connectors/__init__.py
sg_core/connectors/base.py
sg_core/storage/__init__.py
sg_core/storage/store.py
sg_core-0.1.3.dist-info/METADATA
sg_core-0.1.3.dist-info/WHEEL
sg_core-0.1.3.dist-info/RECORD
