Metadata-Version: 2.4
Name: sg-core
Version: 0.1.3
Summary: SluiceGate Open Core
Requires-Python: >=3.11
Requires-Dist: pyyaml>=6.0.1
